dataforest/__init__.py
dataforest/config/MetaConfig.py
dataforest/config/MetaDataProcess.py
dataforest/config/MetaPlotMethods.py
dataforest/config/MetaProcessMethods.py
dataforest/config/MetaProcessSchema.py
dataforest/config/__init__.py
dataforest/config/default_config.yaml
dataforest/core/BranchSpec.py
dataforest/core/DataBase.py
dataforest/core/DataBranch.py
dataforest/core/DataForest.py
dataforest/core/DataMap.py
dataforest/core/DataTree.py
dataforest/core/Interface.py
dataforest/core/PlotMethods.py
dataforest/core/ProcessRun.py
dataforest/core/RunGroupSpec.py
dataforest/core/RunSpec.py
dataforest/core/Spec.py
dataforest/core/Sweep.py
dataforest/core/TreeSpec.py
dataforest/core/__init__.py
dataforest/core/dataprocess.py
dataforest/core/schema/ProcessSchema.py
dataforest/core/schema/__init__.py
dataforest/filesystem/DataTree.py
dataforest/filesystem/FileIO.py
dataforest/filesystem/Tree.py
dataforest/filesystem/__init__.py
dataforest/filesystem/io/FileIO.py
dataforest/filesystem/io/PlotIO.py
dataforest/filesystem/io/ReaderMethods.py
dataforest/filesystem/io/WriterMethods.py
dataforest/filesystem/io/__init__.py
dataforest/filesystem/tree/Tree.py
dataforest/filesystem/tree/__init__.py
dataforest/hooks/__init__.py
dataforest/hooks/hook.py
dataforest/hooks/dataprocess/__init__.py
dataforest/hooks/dataprocess/dataprocess.py
dataforest/hooks/hooks/__init__.py
dataforest/hooks/hooks/core/__init__.py
dataforest/hooks/hooks/core/hooks.py
dataforest/hyperparams/HyperparameterMethods.py
dataforest/hyperparams/Sweep.py
dataforest/hyperparams/__init__.py
dataforest/processes/__init__.py
dataforest/processes/core/BatchMethods.py
dataforest/processes/core/ProcessMethods.py
dataforest/processes/core/TreeProcessMethods.py
dataforest/processes/core/__init__.py
dataforest/processes/processes/__init__.py
dataforest/structures/__init__.py
dataforest/structures/cache/BranchCache.py
dataforest/structures/cache/HashCash.py
dataforest/structures/cache/IOCache.py
dataforest-0.0.2.dist-info/LICENSE
dataforest-0.0.2.dist-info/METADATA
dataforest-0.0.2.dist-info/WHEEL
dataforest-0.0.2.dist-info/top_level.txt
dataforest-0.0.2.dist-info/RECORD
