Metadata-Version: 2.1
Name: dataforest
Version: 0.0.2
Summary: An interactive data science workflow manager
Home-page: https://github.com/TheAustinator/dataforest
Author: Austin McKay
Author-email: austinmckay303@gmail.com
License: UNKNOWN
Platform: UNKNOWN
Classifier: Programming Language :: Python :: 3
Classifier: License :: OSI Approved :: GNU Affero General Public License v3 or later (AGPLv3+)
Classifier: Operating System :: OS Independent
Requires-Python: >=3.6
Requires-Dist: matplotlib
Requires-Dist: numpy
Requires-Dist: pandas
Requires-Dist: pathlib
Requires-Dist: pyyaml
Requires-Dist: termcolor
Requires-Dist: Ipython
Provides-Extra: all
Requires-Dist: matplotlib ; extra == 'all'
Requires-Dist: numpy ; extra == 'all'
Requires-Dist: pandas ; extra == 'all'
Requires-Dist: pathlib ; extra == 'all'
Requires-Dist: pyyaml ; extra == 'all'
Requires-Dist: termcolor ; extra == 'all'
Requires-Dist: Ipython ; extra == 'all'
Provides-Extra: dev
Provides-Extra: test
Requires-Dist: pytest ; extra == 'test'
